ruth/__init__.py
ruth/constants.py
ruth/cli/__init__.py
ruth/cli/cli.py
ruth/cli/utills.py
ruth/nlu/__init__.py
ruth/nlu/config.py
ruth/nlu/constants.py
ruth/nlu/elements.py
ruth/nlu/model.py
ruth/nlu/registry.py
ruth/nlu/train.py
ruth/nlu/utils.py
ruth/nlu/classifiers/__init__.py
ruth/nlu/classifiers/constants.py
ruth/nlu/classifiers/hf_classifier.py
ruth/nlu/classifiers/naive_bayes_classifier.py
ruth/nlu/classifiers/ruth_classifier.py
ruth/nlu/classifiers/svm_classifier.py
ruth/nlu/featurizers/__init__.py
ruth/nlu/featurizers/featurizer.py
ruth/nlu/featurizers/dense_featurizers/__init__.py
ruth/nlu/featurizers/dense_featurizers/dense_featurizer.py
ruth/nlu/featurizers/dense_featurizers/fast_text.py
ruth/nlu/featurizers/sparse_featurizers/__init__.py
ruth/nlu/featurizers/sparse_featurizers/constants.py
ruth/nlu/featurizers/sparse_featurizers/count_vector_featurizer.py
ruth/nlu/featurizers/sparse_featurizers/sparse_featurizer.py
ruth/nlu/featurizers/sparse_featurizers/tfidf_vector_featurizer.py
ruth/nlu/tokenizer/__init__.py
ruth/nlu/tokenizer/constants.py
ruth/nlu/tokenizer/hf_tokenizer.py
ruth/nlu/tokenizer/tokenizer.py
ruth/nlu/tokenizer/whitespace_tokenizer.py
ruth/shared/__init__.py
ruth/shared/constants.py
ruth/shared/utils.py
ruth/shared/nlu/__init__.py
ruth/shared/nlu/training_data/__init__.py
ruth/shared/nlu/training_data/collections.py
ruth/shared/nlu/training_data/feature.py
ruth/shared/nlu/training_data/ruth_config.py
ruth/shared/nlu/training_data/ruth_data.py
ruth/shared/nlu/training_data/tokens.py
ruth/shared/nlu/training_data/utils.py
ruth_py-0.0.5.dist-info/METADATA
ruth_py-0.0.5.dist-info/WHEEL
ruth_py-0.0.5.dist-info/entry_points.txt
ruth_py-0.0.5.dist-info/top_level.txt
ruth_py-0.0.5.dist-info/RECORD
